fastapi_offline/__init__.py
fastapi_offline/consts.py
fastapi_offline/core.py
fastapi_offline/py.typed
fastapi_offline/static/favicon.png
fastapi_offline/static/redoc.standalone.js
fastapi_offline/static/swagger-ui-bundle.js
fastapi_offline/static/swagger-ui.css
wigm_fastapi_offline-1.6.0.dist-info/LICENSE
wigm_fastapi_offline-1.6.0.dist-info/METADATA
wigm_fastapi_offline-1.6.0.dist-info/WHEEL
wigm_fastapi_offline-1.6.0.dist-info/top_level.txt
wigm_fastapi_offline-1.6.0.dist-info/RECORD
