Metadata-Version: 2.1
Name: wigm-fastapi-offline
Version: 1.6.0
Summary: FastAPI without reliance on CDNs for docs
Home-page: https://github.com/turettn/fastapi_offline
Author: Neal Turett
Author-email: turettn@gmail.com
License: MIT
Classifier: License :: OSI Approved :: MIT License
Classifier: Programming Language :: Python :: 3
Classifier: Programming Language :: Python :: 3 :: Only
Requires-Python: >=3.7
License-File: LICENSE
Requires-Dist: fastapi (>=0.99.0)
Provides-Extra: test
Requires-Dist: pytest ; extra == 'test'
Requires-Dist: requests ; extra == 'test'
Requires-Dist: starlette[full] ; extra == 'test'
